LuhnExtended/__init__.py
LuhnExtended-1.0.1.dist-info/LICENSE
LuhnExtended-1.0.1.dist-info/METADATA
LuhnExtended-1.0.1.dist-info/WHEEL
LuhnExtended-1.0.1.dist-info/top_level.txt
LuhnExtended-1.0.1.dist-info/RECORD
