Metadata-Version: 2.1
Name: LuhnExtended
Version: 1.0.1
Summary: A library for advanced Luhn algorithm operations
Author: Luhn Extended
License: MIT
Project-URL: Repository, https://github.com/luhnextended/luhnextended
Keywords: luhn,checksum,verification,generation
Classifier: Development Status :: 5 - Production/Stable
Classifier: Intended Audience :: Developers
Classifier: License :: OSI Approved :: MIT License
Classifier: Programming Language :: Python :: 3
Classifier: Programming Language :: Python :: 3.7
Classifier: Programming Language :: Python :: 3.8
Classifier: Programming Language :: Python :: 3.9
License-File: LICENSE
